clippy_ai/__init__.py
clippy_ai/clippy.py
clippy_ai/templates/base_system.md
clippy_ai/templates/base_test.md
clippy_ai/templates/mac_commands.md
clippy_ai/templates/timesheets.md
clippy_ai/tools/__init__.py
clippy_ai/tools/ai.py
clippy_ai/tools/harvest.py
clippy_ai/tools/tmetric.py
clippy_ai/utils/__init__.py
clippy_ai/utils/config.py
clippy_ai/utils/helper.py
clippy_ai/utils/history.py
clippy_ai/utils/logger.py
clippy_ai-0.1.5.dist-info/LICENSE
clippy_ai-0.1.5.dist-info/METADATA
clippy_ai-0.1.5.dist-info/WHEEL
clippy_ai-0.1.5.dist-info/entry_points.txt
clippy_ai-0.1.5.dist-info/RECORD
