Metadata-Version: 2.3
Name: clippy-ai
Version: 0.1.5
Summary: Clippy AI is a set of command line tools that makes my life easier. YMMV
Author: John Carpenter
Author-email: john@2linessoftware.com
Requires-Python: >=3.10,<4.0
Classifier: Programming Language :: Python :: 3
Classifier: Programming Language :: Python :: 3.10
Classifier: Programming Language :: Python :: 3.11
Classifier: Programming Language :: Python :: 3.12
Classifier: Programming Language :: Python :: 3.13
Requires-Dist: click (>=8.1.8,<9.0.0)
Requires-Dist: jinja2 (>=3.1.5,<4.0.0)
Requires-Dist: langchain (>=0.3.18,<0.4.0)
Requires-Dist: langchain-community (>=0.3.17,<0.4.0)
Requires-Dist: langchain-openai (>=0.3.4,<0.4.0)
